README.md
setup.py
sanjip/__init__.py
sanjip.egg-info/PKG-INFO
sanjip.egg-info/SOURCES.txt
sanjip.egg-info/dependency_links.txt
sanjip.egg-info/requires.txt
sanjip.egg-info/top_level.txt
sanjip/ip/__init__.py
sanjip/ip/addr.py
sanjip/ip/route.py